RockLog/__init__.py
RockLog/app.py
RockLog/functions.py
RockLog/main.py
rocklog-0.1.0.dist-info/LICENSE
rocklog-0.1.0.dist-info/METADATA
rocklog-0.1.0.dist-info/WHEEL
rocklog-0.1.0.dist-info/entry_points.txt
rocklog-0.1.0.dist-info/top_level.txt
rocklog-0.1.0.dist-info/RECORD
