Metadata-Version: 2.1
Name: rocklog
Version: 0.1.0
Summary: collects Logs and presents them in a web app
Home-page: https://github.com/thiloschild/RockLog
Author: Thilo Schild
Author-email: work@thilo-schild.de
License: MIT
Platform: UNKNOWN
Classifier: Programming Language :: Python :: 3
Classifier: License :: OSI Approved :: MIT License
Classifier: Operating System :: OS Independent
Requires-Python: >=3.6
Requires-Dist: pandas
Requires-Dist: dash
Requires-Dist: plotly
Requires-Dist: datetime
